<?xml version="1.0" encoding="UTF-8"?>
<mule xmlns:ee="http://www.mulesoft.org/schema/mule/ee/core" xmlns:wsc="http://www.mulesoft.org/schema/mule/wsc" xmlns:doc="http://www.mulesoft.org/schema/mule/documentation" xmlns="http://www.mulesoft.org/schema/mule/core" xmlns:apikit="http://www.mulesoft.org/schema/mule/mule-apikit" xmlns:http="http://www.mulesoft.org/schema/mule/http" xmlns:xsi="http://www.w3.org/2001/XMLSchema-instance" xsi:schemaLocation="http://www.mulesoft.org/schema/mule/core http://www.mulesoft.org/schema/mule/core/current/mule.xsd http://www.mulesoft.org/schema/mule/http http://www.mulesoft.org/schema/mule/http/current/mule-http.xsd http://www.mulesoft.org/schema/mule/mule-apikit http://www.mulesoft.org/schema/mule/mule-apikit/current/mule-apikit.xsd 
http://www.mulesoft.org/schema/mule/wsc http://www.mulesoft.org/schema/mule/wsc/current/mule-wsc.xsd
http://www.mulesoft.org/schema/mule/ee/core http://www.mulesoft.org/schema/mule/ee/core/current/mule-ee.xsd">
    <http:listener-config name="customer-management-api-httpListenerConfig">
        <http:listener-connection host="${http.host}" port="${http.port}" />
    </http:listener-config>
    <apikit:config name="customer-management-api-config" api="customer-management-api.raml" outboundHeadersMapName="outboundHeaders" httpStatusVarName="httpStatus" />
    <wsc:config name="Web_Service_Consumer_Config" doc:name="Web Service Consumer Config" doc:id="0917bf34-930a-4d50-9ac7-b8eadf26613e" >
		<wsc:connection wsdlLocation="http://api.icraftsoft.net:5858/ws/users.wsdl" service="UserPortService" port="UserPortSoap11" address="http://api.icraftsoft.net:5858/ws" >
			
		</wsc:connection>
	</wsc:config>
	<configuration-properties doc:name="Configuration properties" doc:id="72fbdca5-d428-4216-bef3-02f14cd9047b" file="${env}.yaml" />
	<global-property doc:name="Global Property" doc:id="8b38d491-42bb-43e2-8314-601e35b36a63" name="env" value="UAT" />
	<flow name="customer-management-api-main">
        <http:listener config-ref="customer-management-api-httpListenerConfig" path="/api/*">
            <http:response statusCode="#[vars.httpStatus default 200]">
                <http:headers>#[vars.outboundHeaders default {}]</http:headers>
            </http:response>
            <http:error-response statusCode="#[vars.httpStatus default 500]">
                <http:body>#[payload]</http:body>
                <http:headers>#[vars.outboundHeaders default {}]</http:headers>
            </http:error-response>
        </http:listener>
        <apikit:router config-ref="customer-management-api-config" />
        <error-handler>
            <on-error-propagate type="APIKIT:BAD_REQUEST">
                <ee:transform xmlns:ee="http://www.mulesoft.org/schema/mule/ee/core" xsi:schemaLocation="http://www.mulesoft.org/schema/mule/ee/core http://www.mulesoft.org/schema/mule/ee/core/current/mule-ee.xsd" doc:id="06a634a4-a66b-46a8-b57c-1a0d4e930752">
                    <ee:message>
                        <ee:set-payload><![CDATA[%dw 2.0
output application/json
---
{message: "Bad request"}]]></ee:set-payload>
                    </ee:message>
                    <ee:variables>
                        <ee:set-variable variableName="httpStatus"><![CDATA[400]]></ee:set-variable>
                    </ee:variables>
                </ee:transform>
            </on-error-propagate>
            <on-error-propagate type="APIKIT:NOT_FOUND">
                <ee:transform xmlns:ee="http://www.mulesoft.org/schema/mule/ee/core" xsi:schemaLocation="http://www.mulesoft.org/schema/mule/ee/core http://www.mulesoft.org/schema/mule/ee/core/current/mule-ee.xsd">
                    <ee:message>
                        <ee:set-payload><![CDATA[%dw 2.0
output application/json
---
{message: "Resource not found"}]]></ee:set-payload>
                    </ee:message>
                    <ee:variables>
                        <ee:set-variable variableName="httpStatus">404</ee:set-variable>
                    </ee:variables>
                </ee:transform>
            </on-error-propagate>
            <on-error-propagate type="APIKIT:METHOD_NOT_ALLOWED">
                <ee:transform xmlns:ee="http://www.mulesoft.org/schema/mule/ee/core" xsi:schemaLocation="http://www.mulesoft.org/schema/mule/ee/core http://www.mulesoft.org/schema/mule/ee/core/current/mule-ee.xsd">
                    <ee:message>
                        <ee:set-payload><![CDATA[%dw 2.0
output application/json
---
{message: "Method not allowed"}]]></ee:set-payload>
                    </ee:message>
                    <ee:variables>
                        <ee:set-variable variableName="httpStatus">405</ee:set-variable>
                    </ee:variables>
                </ee:transform>
            </on-error-propagate>
            <on-error-propagate type="APIKIT:NOT_ACCEPTABLE">
                <ee:transform xmlns:ee="http://www.mulesoft.org/schema/mule/ee/core" xsi:schemaLocation="http://www.mulesoft.org/schema/mule/ee/core http://www.mulesoft.org/schema/mule/ee/core/current/mule-ee.xsd">
                    <ee:message>
                        <ee:set-payload><![CDATA[%dw 2.0
output application/json
---
{message: "Not acceptable"}]]></ee:set-payload>
                    </ee:message>
                    <ee:variables>
                        <ee:set-variable variableName="httpStatus">406</ee:set-variable>
                    </ee:variables>
                </ee:transform>
            </on-error-propagate>
            <on-error-propagate type="APIKIT:UNSUPPORTED_MEDIA_TYPE">
                <ee:transform xmlns:ee="http://www.mulesoft.org/schema/mule/ee/core" xsi:schemaLocation="http://www.mulesoft.org/schema/mule/ee/core http://www.mulesoft.org/schema/mule/ee/core/current/mule-ee.xsd">
                    <ee:message>
                        <ee:set-payload><![CDATA[%dw 2.0
output application/json
---
{message: "Unsupported media type"}]]></ee:set-payload>
                    </ee:message>
                    <ee:variables>
                        <ee:set-variable variableName="httpStatus">415</ee:set-variable>
                    </ee:variables>
                </ee:transform>
            </on-error-propagate>
            <on-error-propagate type="APIKIT:NOT_IMPLEMENTED">
                <ee:transform xmlns:ee="http://www.mulesoft.org/schema/mule/ee/core" xsi:schemaLocation="http://www.mulesoft.org/schema/mule/ee/core http://www.mulesoft.org/schema/mule/ee/core/current/mule-ee.xsd">
                    <ee:message>
                        <ee:set-payload><![CDATA[%dw 2.0
output application/json
---
{message: "Not Implemented"}]]></ee:set-payload>
                    </ee:message>
                    <ee:variables>
                        <ee:set-variable variableName="httpStatus">501</ee:set-variable>
                    </ee:variables>
                </ee:transform>
            </on-error-propagate>
        </error-handler>
    </flow>
    <flow name="customer-management-api-console">
        <http:listener config-ref="customer-management-api-httpListenerConfig" path="/console/*">
            <http:response statusCode="#[vars.httpStatus default 200]">
                <http:headers>#[vars.outboundHeaders default {}]</http:headers>
            </http:response>
            <http:error-response statusCode="#[vars.httpStatus default 500]">
                <http:body>#[payload]</http:body>
                <http:headers>#[vars.outboundHeaders default {}]</http:headers>
            </http:error-response>
        </http:listener>
        <apikit:console config-ref="customer-management-api-config" />
        <error-handler>
            <on-error-propagate type="APIKIT:NOT_FOUND">
                <ee:transform xmlns:ee="http://www.mulesoft.org/schema/mule/ee/core" xsi:schemaLocation="http://www.mulesoft.org/schema/mule/ee/core http://www.mulesoft.org/schema/mule/ee/core/current/mule-ee.xsd">
                    <ee:message>
                        <ee:set-payload><![CDATA[%dw 2.0
output application/json
---
{message: "Resource not found"}]]></ee:set-payload>
                    </ee:message>
                    <ee:variables>
                        <ee:set-variable variableName="httpStatus">404</ee:set-variable>
                    </ee:variables>
                </ee:transform>
            </on-error-propagate>
        </error-handler>
    </flow>
    <flow name="put:\users:application\json:customer-management-api-config">
		<flow-ref doc:name="updateuserflow" doc:id="8f67bb81-0f4f-464e-b8af-1528e4be5c6f" name="updateuserflow"/>
    </flow>
    <flow name="delete:\users\(id):application\json:customer-management-api-config">
		<flow-ref doc:name="deletuserflow" doc:id="b0badbb0-4ca1-4ff3-b66c-27721fe8d322" name="deletuserflow"/>
    </flow>
    <flow name="get:\users:customer-management-api-config">
		<flow-ref doc:name="getallusersflow" doc:id="9615d85a-7cd0-4adc-9c86-f9d26f5849a6" name="getallusersflow"/>
    </flow>
    <flow name="get:\users\(id):customer-management-api-config">
		<flow-ref doc:name="getuserbyidflow" doc:id="d330f2e3-47ee-45d9-851d-acc884535366" name="getuserbyidflow"/>
    </flow>
    <flow name="post:\users:application\json:customer-management-api-config">
		<flow-ref doc:name="creatuserflow" doc:id="88d1de48-d2b4-4103-87dd-2d242298a040" name="creatuserflow"/>
    </flow>
</mule>
